madashboard/__init__.py
madashboard/admin.py
madashboard/app_settings.py
madashboard/apps.py
madashboard/auth_hooks.py
madashboard/decorators.py
madashboard/errors.py
madashboard/forms.py
madashboard/models.py
madashboard/providers.py
madashboard/tasks.py
madashboard/urls.py
madashboard/views.py
madashboard/locale/django.pot
madashboard/locale/cs_CZ/LC_MESSAGES/django.mo
madashboard/locale/cs_CZ/LC_MESSAGES/django.po
madashboard/locale/de/LC_MESSAGES/django.mo
madashboard/locale/de/LC_MESSAGES/django.po
madashboard/locale/es/LC_MESSAGES/django.mo
madashboard/locale/es/LC_MESSAGES/django.po
madashboard/locale/fr_FR/LC_MESSAGES/django.mo
madashboard/locale/fr_FR/LC_MESSAGES/django.po
madashboard/locale/it_IT/LC_MESSAGES/django.mo
madashboard/locale/it_IT/LC_MESSAGES/django.po
madashboard/locale/ja/LC_MESSAGES/django.mo
madashboard/locale/ja/LC_MESSAGES/django.po
madashboard/locale/ko_KR/LC_MESSAGES/django.mo
madashboard/locale/ko_KR/LC_MESSAGES/django.po
madashboard/locale/nl_NL/LC_MESSAGES/django.mo
madashboard/locale/nl_NL/LC_MESSAGES/django.po
madashboard/locale/pl_PL/LC_MESSAGES/django.mo
madashboard/locale/pl_PL/LC_MESSAGES/django.po
madashboard/locale/ru/LC_MESSAGES/django.mo
madashboard/locale/ru/LC_MESSAGES/django.po
madashboard/locale/sk/LC_MESSAGES/django.mo
madashboard/locale/sk/LC_MESSAGES/django.po
madashboard/locale/uk/LC_MESSAGES/django.mo
madashboard/locale/uk/LC_MESSAGES/django.po
madashboard/locale/zh_Hans/LC_MESSAGES/django.mo
madashboard/locale/zh_Hans/LC_MESSAGES/django.po
madashboard/migrations/__init__.py
madashboard/templates/madashboard/dashboard.html
madashboard/tests/__init__.py
madashboard/tests/test_auth_hook.py
madashboard/tests/test_views.py
madashboard/tests/testdata/allianceauth.json
madashboard/tests/testdata/esi.json
madashboard/tests/testdata/esi_stub.py
madashboard/tests/testdata/eveentity.json
madashboard/tests/testdata/eveuniverse.json
madashboard/tests/testdata/load_allianceauth.py
madashboard/tests/testdata/load_eveuniverse.py
aa_memberaudit_dashboard-1.1.3.dist-info/METADATA
aa_memberaudit_dashboard-1.1.3.dist-info/WHEEL
aa_memberaudit_dashboard-1.1.3.dist-info/licenses/LICENSE
aa_memberaudit_dashboard-1.1.3.dist-info/RECORD
