Metadata-Version: 2.4
Name: aa-memberaudit-dashboard
Version: 1.1.3
Summary: Dashboard Addon for Member Audit
Project-URL: Changelog, https://github.com/Geuthur/aa-memberaudit-dashboard/blob/master/CHANGELOG.md
Project-URL: Documentation, https://github.com/Geuthur/aa-memberaudit-dashboard/blob/master/README.md
Project-URL: Donations, https://ko-fi.com/Geuthur
Project-URL: Homepage, https://github.com/Geuthur/aa-memberaudit-dashboard
Project-URL: Source, https://github.com/Geuthur/aa-memberaudit-dashboard
Project-URL: Tracker, https://github.com/Geuthur/aa-memberaudit-dashboard/issues
Author-email: Geuthur <devgeuthur@gmail.com>
License:                     GNU GENERAL PUBLIC LICENSE
License-File: LICENSE
Classifier: Environment :: Web Environment
Classifier: Framework :: Django
Classifier: Framework :: Django :: 4.2
Classifier: Intended Audience :: Developers
Classifier: License :: OSI Approved :: GNU General Public License v3 (GPLv3)
Classifier: Operating System :: OS Independent
Classifier: Programming Language :: Python
Classifier: Programming Language :: Python :: 3 :: Only
Classifier: Programming Language :: Python :: 3.10
Classifier: Programming Language :: Python :: 3.11
Classifier: Programming Language :: Python :: 3.12
Classifier: Programming Language :: Python :: 3.13
Classifier: Topic :: Internet :: WWW/HTTP
Classifier: Topic :: Internet :: WWW/HTTP :: Dynamic Content
Requires-Python: >=3.10
Requires-Dist: aa-memberaudit
Requires-Dist: allianceauth-app-utils>=1.26
Requires-Dist: allianceauth<5,>=4.8
Provides-Extra: tests-allianceauth-latest
Requires-Dist: coverage; extra == 'tests-allianceauth-latest'
Requires-Dist: factory-boy; extra == 'tests-allianceauth-latest'
